bareasgi_cors/__init__.py
bareasgi_cors/cors_provider.py
bareasgi_cors/helpers.py
bareasgi_cors/py.typed
bareasgi_cors-4.1.0.dist-info/LICENSE
bareasgi_cors-4.1.0.dist-info/WHEEL
bareasgi_cors-4.1.0.dist-info/METADATA
bareasgi_cors-4.1.0.dist-info/RECORD
